nice/__init__.py
nice/column.py
nice/database.py
nice/dtypes.py
nice/parser.py
nice/query.py
nice/table.py
nice_parser-0.0.2.dist-info/LICENSE
nice_parser-0.0.2.dist-info/METADATA
nice_parser-0.0.2.dist-info/WHEEL
nice_parser-0.0.2.dist-info/top_level.txt
nice_parser-0.0.2.dist-info/RECORD
