Metadata-Version: 2.1
Name: nice-parser
Version: 0.0.2
Summary: Identifique e gere querys para normalização de JSONs via AWS Athena
Author: Leonardo Alves
Author-email: leonardo.as@compasso.com
Classifier: Programming Language :: Python :: 3
Classifier: License :: OSI Approved :: MIT License
Classifier: Operating System :: OS Independent
Requires-Python: >=3.7
License-File: LICENSE
